{
    "zones_with_problems":[null],
    "date": "20240117",
    "url": "https://www.google.com/url?sa=t&source=web&rct=j&opi=89978449&url=http://www.cubadebate.cu/noticias/2024/01/17/union-electrica-preve-afectaciones-durante-todo-el-dia-750-mw-para-el-horario-pico/&ved=2ahUKEwi5gIm6lviJAxXQVTABHTAiNYgQFnoECBkQAQ&usg=AOvVaw1g2L0BRDG2Gna4fZ18TByr",
    "prediction":{
        "availability": 2220,
        "demand_max": 2900,
        "impact": 750,
        "deficit": 680,
        "backup": null
    },
    "morning_info":{
        "time": "0700",
        "availability": 1980,
        "demand": 2040,
        "deficit": null
    },
    "plants":[
        {
            "broken": [
                {
                    "EG":["2"],
                    "LR":["2"]
                }
            ],
            "maintenance": [
                {
                    "MG":["8"],
                    "CM":["3"]
                }
            ],
            "limitation": 427
        }
    ],
    "distributed":{
        "motors_with_problems": null,
        "total_impact": 240,
        "combustible_problem": true,
        "ships_with_problems": 2,
        "motors_impact": null
    },
    "impact": {
        "total_hours": "0315",
        "max": 416,
        "max_hour": "1830"
    }
}
